adafruit_circuitpython_led_animation-2.12.3.dist-info/licenses/LICENSE
adafruit_led_animation/__init__.py
adafruit_led_animation/color.py
adafruit_led_animation/grid.py
adafruit_led_animation/group.py
adafruit_led_animation/helper.py
adafruit_led_animation/pulse_generator.py
adafruit_led_animation/sequence.py
adafruit_led_animation/timedsequence.py
adafruit_led_animation/animation/__init__.py
adafruit_led_animation/animation/blink.py
adafruit_led_animation/animation/chase.py
adafruit_led_animation/animation/colorcycle.py
adafruit_led_animation/animation/comet.py
adafruit_led_animation/animation/customcolorchase.py
adafruit_led_animation/animation/grid_rain.py
adafruit_led_animation/animation/multicolor_comet.py
adafruit_led_animation/animation/pacman.py
adafruit_led_animation/animation/pulse.py
adafruit_led_animation/animation/rainbow.py
adafruit_led_animation/animation/rainbowchase.py
adafruit_led_animation/animation/rainbowcomet.py
adafruit_led_animation/animation/rainbowsparkle.py
adafruit_led_animation/animation/solid.py
adafruit_led_animation/animation/sparkle.py
adafruit_led_animation/animation/sparklepulse.py
adafruit_led_animation/animation/volume.py
adafruit_circuitpython_led_animation-2.12.3.dist-info/METADATA
adafruit_circuitpython_led_animation-2.12.3.dist-info/WHEEL
adafruit_circuitpython_led_animation-2.12.3.dist-info/top_level.txt
adafruit_circuitpython_led_animation-2.12.3.dist-info/RECORD
