Metadata-Version: 2.4
Name: adafruit-circuitpython-led-animation
Version: 2.12.3
Summary: CircuitPython helper for LED colors and animations.
Author-email: Adafruit Industries <circuitpython@adafruit.com>
License: MIT
Project-URL: Homepage, https://github.com/adafruit/Adafruit_CircuitPython_LED_Animation
Keywords: adafruit,blinka,circuitpython,micropython,led,animation,led,colors,animations
Classifier: Intended Audience :: Developers
Classifier: Topic :: Software Development :: Libraries
Classifier: Topic :: Software Development :: Embedded Systems
Classifier: Topic :: System :: Hardware
Classifier: License :: OSI Approved :: MIT License
Classifier: Programming Language :: Python :: 3
License-File: LICENSE
Requires-Dist: Adafruit-Blinka
Provides-Extra: optional
Dynamic: license-file
